{
  "alert": {
    "requiredProps": [],
    "supportedProps": [
      "aria-expanded",
      "aria-atomic",
      "aria-busy",
      "aria-controls",
      "aria-describedby",
      "aria-disabled",
      "aria-dropeffect",
      "aria-flowto",
      "aria-grabbed",
      "aria-haspopup",
      "aria-hidden",
      "aria-invalid",
      "aria-label",
      "aria-labelledby",
      "aria-live",
      "aria-owns",
      "aria-relevant"
    ],
    "isAbstract": false
  },
  "alertdialog": {
    "requiredProps": [],
    "supportedProps": [
      "aria-expanded",
      "aria-atomic",
      "aria-busy",
      "aria-controls",
      "aria-describedby",
      "aria-disabled",
      "aria-dropeffect",
      "aria-flowto",
      "aria-grabbed",
      "aria-haspopup",
      "aria-hidden",
      "aria-invalid",
      "aria-label",
      "aria-labelledby",
      "aria-live",
      "aria-owns",
      "aria-relevant"
    ],
    "isAbstract": false
  },
  "application": {
    "requiredProps": [],
    "supportedProps": [
      "aria-expanded",
      "aria-atomic",
      "aria-busy",
      "aria-controls",
      "aria-describedby",
      "aria-disabled",
      "aria-dropeffect",
      "aria-flowto",
      "aria-grabbed",
      "aria-haspopup",
      "aria-hidden",
      "aria-invalid",
      "aria-label",
      "aria-labelledby",
      "aria-live",
      "aria-owns",
      "aria-relevant"
    ],
    "isAbstract": false
  },
  "article": {
    "requiredProps": [],
    "supportedProps": [
      "aria-expanded",
      "aria-atomic",
      "aria-busy",
      "aria-controls",
      "aria-describedby",
      "aria-disabled",
      "aria-dropeffect",
      "aria-flowto",
      "aria-grabbed",
      "aria-haspopup",
      "aria-hidden",
      "aria-invalid",
      "aria-label",
      "aria-labelledby",
      "aria-live",
      "aria-owns",
      "aria-relevant"
    ],
    "isAbstract": false
  },
  "banner": {
    "requiredProps": [],
    "supportedProps": [
      "aria-expanded",
      "aria-atomic",
      "aria-busy",
      "aria-controls",
      "aria-describedby",
      "aria-disabled",
      "aria-dropeffect",
      "aria-flowto",
      "aria-grabbed",
      "aria-haspopup",
      "aria-hidden",
      "aria-invalid",
      "aria-label",
      "aria-labelledby",
      "aria-live",
      "aria-owns",
      "aria-relevant"
    ],
    "isAbstract": false
  },
  "button": {
    "requiredProps": [],
    "supportedProps": [
      "aria-expanded",
      "aria-pressed",
      "aria-atomic",
      "aria-busy",
      "aria-controls",
      "aria-describedby",
      "aria-disabled",
      "aria-dropeffect",
      "aria-flowto",
      "aria-grabbed",
      "aria-haspopup",
      "aria-hidden",
      "aria-invalid",
      "aria-label",
      "aria-labelledby",
      "aria-live",
      "aria-owns",
      "aria-relevant"
    ],
    "isAbstract": false
  },
  "checkbox": {
    "requiredProps": [
      "aria-checked"
    ],
    "supportedProps": [
      "aria-checked",
      "aria-atomic",
      "aria-busy",
      "aria-controls",
      "aria-describedby",
      "aria-disabled",
      "aria-dropeffect",
      "aria-flowto",
      "aria-grabbed",
      "aria-haspopup",
      "aria-hidden",
      "aria-invalid",
      "aria-label",
      "aria-labelledby",
      "aria-live",
      "aria-owns",
      "aria-relevant"
    ],
    "isAbstract": false
  },
  "columnheader": {
    "requiredProps": [],
    "supportedProps": [
      "aria-sort",
      "aria-readonly",
      "aria-required",
      "aria-selected",
      "aria-expanded",
      "aria-atomic",
      "aria-busy",
      "aria-controls",
      "aria-describedby",
      "aria-disabled",
      "aria-dropeffect",
      "aria-flowto",
      "aria-grabbed",
      "aria-haspopup",
      "aria-hidden",
      "aria-invalid",
      "aria-label",
      "aria-labelledby",
      "aria-live",
      "aria-owns",
      "aria-relevant"
    ],
    "isAbstract": false
  },
  "combobox": {
    "requiredProps": [
      "aria-expanded"
    ],
    "supportedProps": [
      "aria-expanded",
      "aria-autocomplete",
      "aria-required",
      "aria-activedescendant",
      "aria-atomic",
      "aria-busy",
      "aria-controls",
      "aria-describedby",
      "aria-disabled",
      "aria-dropeffect",
      "aria-flowto",
      "aria-grabbed",
      "aria-haspopup",
      "aria-hidden",
      "aria-invalid",
      "aria-label",
      "aria-labelledby",
      "aria-live",
      "aria-owns",
      "aria-relevant"
    ],
    "isAbstract": false
  },
  "command": {
    "supportedProps": [
      "aria-atomic",
      "aria-busy",
      "aria-controls",
      "aria-describedby",
      "aria-disabled",
      "aria-dropeffect",
      "aria-flowto",
      "aria-grabbed",
      "aria-haspopup",
      "aria-hidden",
      "aria-invalid",
      "aria-label",
      "aria-labelledby",
      "aria-live",
      "aria-owns",
      "aria-relevant"
    ],
    "requiredProps": [],
    "isAbstract": true
  },
  "complementary": {
    "requiredProps": [],
    "supportedProps": [
      "aria-expanded",
      "aria-atomic",
      "aria-busy",
      "aria-controls",
      "aria-describedby",
      "aria-disabled",
      "aria-dropeffect",
      "aria-flowto",
      "aria-grabbed",
      "aria-haspopup",
      "aria-hidden",
      "aria-invalid",
      "aria-label",
      "aria-labelledby",
      "aria-live",
      "aria-owns",
      "aria-relevant"
    ],
    "isAbstract": false
  },
  "composite": {
    "supportedProps": [
      "aria-activedescendant",
      "aria-atomic",
      "aria-busy",
      "aria-controls",
      "aria-describedby",
      "aria-disabled",
      "aria-dropeffect",
      "aria-flowto",
      "aria-grabbed",
      "aria-haspopup",
      "aria-hidden",
      "aria-invalid",
      "aria-label",
      "aria-labelledby",
      "aria-live",
      "aria-owns",
      "aria-relevant"
    ],
    "requiredProps": [],
    "isAbstract": true
  },
  "contentinfo": {
    "requiredProps": [],
    "supportedProps": [
      "aria-expanded",
      "aria-atomic",
      "aria-busy",
      "aria-controls",
      "aria-describedby",
      "aria-disabled",
      "aria-dropeffect",
      "aria-flowto",
      "aria-grabbed",
      "aria-haspopup",
      "aria-hidden",
      "aria-invalid",
      "aria-label",
      "aria-labelledby",
      "aria-live",
      "aria-owns",
      "aria-relevant"
    ],
    "isAbstract": false
  },
  "definition": {
    "requiredProps": [],
    "supportedProps": [
      "aria-expanded",
      "aria-atomic",
      "aria-busy",
      "aria-controls",
      "aria-describedby",
      "aria-disabled",
      "aria-dropeffect",
      "aria-flowto",
      "aria-grabbed",
      "aria-haspopup",
      "aria-hidden",
      "aria-invalid",
      "aria-label",
      "aria-labelledby",
      "aria-live",
      "aria-owns",
      "aria-relevant"
    ],
    "isAbstract": false
  },
  "dialog": {
    "requiredProps": [],
    "supportedProps": [
      "aria-expanded",
      "aria-atomic",
      "aria-busy",
      "aria-controls",
      "aria-describedby",
      "aria-disabled",
      "aria-dropeffect",
      "aria-flowto",
      "aria-grabbed",
      "aria-haspopup",
      "aria-hidden",
      "aria-invalid",
      "aria-label",
      "aria-labelledby",
      "aria-live",
      "aria-owns",
      "aria-relevant"
    ],
    "isAbstract": false
  },
  "directory": {
    "requiredProps": [],
    "isAbstract": false,
    "supportedProps": [
      "aria-expanded",
      "aria-atomic",
      "aria-busy",
      "aria-controls",
      "aria-describedby",
      "aria-disabled",
      "aria-dropeffect",
      "aria-flowto",
      "aria-grabbed",
      "aria-haspopup",
      "aria-hidden",
      "aria-invalid",
      "aria-label",
      "aria-labelledby",
      "aria-live",
      "aria-owns",
      "aria-relevant"
    ]
  },
  "doc-abstract": {
    "supportedProps": [
      "aria-atomic",
      "aria-busy",
      "aria-controls",
      "aria-current",
      "aria-describedat",
      "aria-describedby",
      "aria-disabled",
      "aria-dropeffect",
      "aria-expanded",
      "aria-flowto",
      "aria-grabbed",
      "aria-haspopup",
      "aria-hidden",
      "aria-invalid",
      "aria-label",
      "aria-labelledby",
      "aria-live",
      "aria-owns",
      "aria-relevant"
    ],
    "requiredProps": [],
    "isAbstract": false
  },
  "doc-acknowledgments": {
    "supportedProps": [
      "aria-atomic",
      "aria-busy",
      "aria-controls",
      "aria-current",
      "aria-describedat",
      "aria-describedby",
      "aria-disabled",
      "aria-dropeffect",
      "aria-expanded",
      "aria-flowto",
      "aria-grabbed",
      "aria-haspopup",
      "aria-hidden",
      "aria-invalid",
      "aria-label",
      "aria-labelledby",
      "aria-live",
      "aria-owns",
      "aria-relevant"
    ],
    "requiredProps": [],
    "isAbstract": false
  },
  "doc-afterword": {
    "supportedProps": [
      "aria-atomic",
      "aria-busy",
      "aria-controls",
      "aria-current",
      "aria-describedat",
      "aria-describedby",
      "aria-disabled",
      "aria-dropeffect",
      "aria-expanded",
      "aria-flowto",
      "aria-grabbed",
      "aria-haspopup",
      "aria-hidden",
      "aria-invalid",
      "aria-label",
      "aria-labelledby",
      "aria-live",
      "aria-owns",
      "aria-relevant"
    ],
    "requiredProps": [],
    "isAbstract": false
  },
  "doc-appendix": {
    "supportedProps": [
      "aria-atomic",
      "aria-busy",
      "aria-controls",
      "aria-current",
      "aria-describedat",
      "aria-describedby",
      "aria-disabled",
      "aria-dropeffect",
      "aria-expanded",
      "aria-flowto",
      "aria-grabbed",
      "aria-haspopup",
      "aria-hidden",
      "aria-invalid",
      "aria-label",
      "aria-labelledby",
      "aria-live",
      "aria-owns",
      "aria-relevant"
    ],
    "requiredProps": [],
    "isAbstract": false
  },
  "doc-backlink": {
    "supportedProps": [
      "aria-atomic",
      "aria-busy",
      "aria-controls",
      "aria-current",
      "aria-describedat",
      "aria-describedby",
      "aria-disabled",
      "aria-dropeffect",
      "aria-expanded",
      "aria-flowto",
      "aria-grabbed",
      "aria-haspopup",
      "aria-hidden",
      "aria-invalid",
      "aria-label",
      "aria-labelledby",
      "aria-live",
      "aria-owns",
      "aria-relevant"
    ],
    "requiredProps": [],
    "isAbstract": false
  },
  "doc-biblioentry": {
    "supportedProps": [
      "aria-atomic",
      "aria-busy",
      "aria-controls",
      "aria-current",
      "aria-describedat",
      "aria-describedby",
      "aria-disabled",
      "aria-dropeffect",
      "aria-expanded",
      "aria-flowto",
      "aria-grabbed",
      "aria-haspopup",
      "aria-hidden",
      "aria-invalid",
      "aria-label",
      "aria-labelledby",
      "aria-level",
      "aria-live",
      "aria-owns",
      "aria-posinset",
      "aria-relevant",
      "aria-setsize"
    ],
    "requiredProps": [],
    "isAbstract": false
  },
  "doc-bibliography": {
    "supportedProps": [
      "aria-atomic",
      "aria-busy",
      "aria-controls",
      "aria-current",
      "aria-describedat",
      "aria-describedby",
      "aria-disabled",
      "aria-dropeffect",
      "aria-expanded",
      "aria-flowto",
      "aria-grabbed",
      "aria-haspopup",
      "aria-hidden",
      "aria-invalid",
      "aria-label",
      "aria-labelledby",
      "aria-live",
      "aria-owns",
      "aria-relevant"
    ],
    "requiredProps": [],
    "isAbstract": false
  },
  "doc-biblioref": {
    "supportedProps": [
      "aria-atomic",
      "aria-busy",
      "aria-controls",
      "aria-current",
      "aria-describedat",
      "aria-describedby",
      "aria-disabled",
      "aria-dropeffect",
      "aria-expanded",
      "aria-flowto",
      "aria-grabbed",
      "aria-haspopup",
      "aria-hidden",
      "aria-invalid",
      "aria-label",
      "aria-labelledby",
      "aria-live",
      "aria-owns",
      "aria-relevant"
    ],
    "requiredProps": [],
    "isAbstract": false
  },
  "doc-chapter": {
    "supportedProps": [
      "aria-atomic",
      "aria-busy",
      "aria-controls",
      "aria-current",
      "aria-describedat",
      "aria-describedby",
      "aria-disabled",
      "aria-dropeffect",
      "aria-expanded",
      "aria-flowto",
      "aria-grabbed",
      "aria-haspopup",
      "aria-hidden",
      "aria-invalid",
      "aria-label",
      "aria-labelledby",
      "aria-live",
      "aria-owns",
      "aria-relevant"
    ],
    "requiredProps": [],
    "isAbstract": false
  },
  "doc-colophon": {
    "supportedProps": [
      "aria-atomic",
      "aria-busy",
      "aria-controls",
      "aria-current",
      "aria-describedat",
      "aria-describedby",
      "aria-disabled",
      "aria-dropeffect",
      "aria-expanded",
      "aria-flowto",
      "aria-grabbed",
      "aria-haspopup",
      "aria-hidden",
      "aria-invalid",
      "aria-label",
      "aria-labelledby",
      "aria-live",
      "aria-owns",
      "aria-relevant"
    ],
    "requiredProps": [],
    "isAbstract": false
  },
  "doc-conclusion": {
    "supportedProps": [
      "aria-atomic",
      "aria-busy",
      "aria-controls",
      "aria-current",
      "aria-describedat",
      "aria-describedby",
      "aria-disabled",
      "aria-dropeffect",
      "aria-expanded",
      "aria-flowto",
      "aria-grabbed",
      "aria-haspopup",
      "aria-hidden",
      "aria-invalid",
      "aria-label",
      "aria-labelledby",
      "aria-live",
      "aria-owns",
      "aria-relevant"
    ],
    "requiredProps": [],
    "isAbstract": false
  },
  "doc-cover": {
    "supportedProps": [
      "aria-atomic",
      "aria-busy",
      "aria-controls",
      "aria-current",
      "aria-describedat",
      "aria-describedby",
      "aria-disabled",
      "aria-dropeffect",
      "aria-expanded",
      "aria-flowto",
      "aria-grabbed",
      "aria-haspopup",
      "aria-hidden",
      "aria-invalid",
      "aria-label",
      "aria-labelledby",
      "aria-live",
      "aria-owns",
      "aria-relevant"
    ],
    "requiredProps": [],
    "isAbstract": false
  },
  "doc-credit": {
    "supportedProps": [
      "aria-atomic",
      "aria-busy",
      "aria-controls",
      "aria-current",
      "aria-describedat",
      "aria-describedby",
      "aria-disabled",
      "aria-dropeffect",
      "aria-expanded",
      "aria-flowto",
      "aria-grabbed",
      "aria-haspopup",
      "aria-hidden",
      "aria-invalid",
      "aria-label",
      "aria-labelledby",
      "aria-live",
      "aria-owns",
      "aria-relevant"
    ],
    "requiredProps": [],
    "isAbstract": false
  },
  "doc-credits": {
    "supportedProps": [
      "aria-atomic",
      "aria-busy",
      "aria-controls",
      "aria-current",
      "aria-describedat",
      "aria-describedby",
      "aria-disabled",
      "aria-dropeffect",
      "aria-expanded",
      "aria-flowto",
      "aria-grabbed",
      "aria-haspopup",
      "aria-hidden",
      "aria-invalid",
      "aria-label",
      "aria-labelledby",
      "aria-live",
      "aria-owns",
      "aria-relevant"
    ],
    "requiredProps": [],
    "isAbstract": false
  },
  "doc-dedication": {
    "supportedProps": [
      "aria-atomic",
      "aria-busy",
      "aria-controls",
      "aria-current",
      "aria-describedat",
      "aria-describedby",
      "aria-disabled",
      "aria-dropeffect",
      "aria-expanded",
      "aria-flowto",
      "aria-grabbed",
      "aria-haspopup",
      "aria-hidden",
      "aria-invalid",
      "aria-label",
      "aria-labelledby",
      "aria-live",
      "aria-owns",
      "aria-relevant"
    ],
    "requiredProps": [],
    "isAbstract": false
  },
  "doc-endnote": {
    "supportedProps": [
      "aria-atomic",
      "aria-busy",
      "aria-controls",
      "aria-current",
      "aria-describedat",
      "aria-describedby",
      "aria-disabled",
      "aria-dropeffect",
      "aria-expanded",
      "aria-flowto",
      "aria-grabbed",
      "aria-haspopup",
      "aria-hidden",
      "aria-invalid",
      "aria-label",
      "aria-labelledby",
      "aria-level",
      "aria-live",
      "aria-owns",
      "aria-posinset",
      "aria-relevant",
      "aria-setsize"
    ],
    "requiredProps": [],
    "isAbstract": false
  },
  "doc-endnotes": {
    "supportedProps": [
      "aria-atomic",
      "aria-busy",
      "aria-controls",
      "aria-current",
      "aria-describedat",
      "aria-describedby",
      "aria-disabled",
      "aria-dropeffect",
      "aria-expanded",
      "aria-flowto",
      "aria-grabbed",
      "aria-haspopup",
      "aria-hidden",
      "aria-invalid",
      "aria-label",
      "aria-labelledby",
      "aria-live",
      "aria-owns",
      "aria-relevant"
    ],
    "requiredProps": [],
    "isAbstract": false
  },
  "doc-epigraph": {
    "supportedProps": [
      "aria-atomic",
      "aria-busy",
      "aria-controls",
      "aria-current",
      "aria-describedat",
      "aria-describedby",
      "aria-disabled",
      "aria-dropeffect",
      "aria-expanded",
      "aria-flowto",
      "aria-grabbed",
      "aria-haspopup",
      "aria-hidden",
      "aria-invalid",
      "aria-label",
      "aria-labelledby",
      "aria-live",
      "aria-owns",
      "aria-relevant"
    ],
    "requiredProps": [],
    "isAbstract": false
  },
  "doc-epilogue": {
    "supportedProps": [
      "aria-atomic",
      "aria-busy",
      "aria-controls",
      "aria-current",
      "aria-describedat",
      "aria-describedby",
      "aria-disabled",
      "aria-dropeffect",
      "aria-expanded",
      "aria-flowto",
      "aria-grabbed",
      "aria-haspopup",
      "aria-hidden",
      "aria-invalid",
      "aria-label",
      "aria-labelledby",
      "aria-live",
      "aria-owns",
      "aria-relevant"
    ],
    "requiredProps": [],
    "isAbstract": false
  },
  "doc-errata": {
    "supportedProps": [
      "aria-atomic",
      "aria-busy",
      "aria-controls",
      "aria-current",
      "aria-describedat",
      "aria-describedby",
      "aria-disabled",
      "aria-dropeffect",
      "aria-expanded",
      "aria-flowto",
      "aria-grabbed",
      "aria-haspopup",
      "aria-hidden",
      "aria-invalid",
      "aria-label",
      "aria-labelledby",
      "aria-live",
      "aria-owns",
      "aria-relevant"
    ],
    "requiredProps": [],
    "isAbstract": false
  },
  "doc-example": {
    "supportedProps": [
      "aria-atomic",
      "aria-busy",
      "aria-controls",
      "aria-current",
      "aria-describedat",
      "aria-describedby",
      "aria-disabled",
      "aria-dropeffect",
      "aria-expanded",
      "aria-flowto",
      "aria-grabbed",
      "aria-haspopup",
      "aria-hidden",
      "aria-invalid",
      "aria-label",
      "aria-labelledby",
      "aria-live",
      "aria-owns",
      "aria-relevant"
    ],
    "requiredProps": [],
    "isAbstract": false
  },
  "doc-footnote": {
    "supportedProps": [
      "aria-atomic",
      "aria-busy",
      "aria-controls",
      "aria-current",
      "aria-describedat",
      "aria-describedby",
      "aria-disabled",
      "aria-dropeffect",
      "aria-expanded",
      "aria-flowto",
      "aria-grabbed",
      "aria-haspopup",
      "aria-hidden",
      "aria-invalid",
      "aria-label",
      "aria-labelledby",
      "aria-live",
      "aria-owns",
      "aria-relevant"
    ],
    "requiredProps": [],
    "isAbstract": false
  },
  "doc-foreword": {
    "supportedProps": [
      "aria-atomic",
      "aria-busy",
      "aria-controls",
      "aria-current",
      "aria-describedat",
      "aria-describedby",
      "aria-disabled",
      "aria-dropeffect",
      "aria-expanded",
      "aria-flowto",
      "aria-grabbed",
      "aria-haspopup",
      "aria-hidden",
      "aria-invalid",
      "aria-label",
      "aria-labelledby",
      "aria-live",
      "aria-owns",
      "aria-relevant"
    ],
    "requiredProps": [],
    "isAbstract": false
  },
  "doc-glossary": {
    "supportedProps": [
      "aria-atomic",
      "aria-busy",
      "aria-controls",
      "aria-current",
      "aria-describedat",
      "aria-describedby",
      "aria-disabled",
      "aria-dropeffect",
      "aria-expanded",
      "aria-flowto",
      "aria-grabbed",
      "aria-haspopup",
      "aria-hidden",
      "aria-invalid",
      "aria-label",
      "aria-labelledby",
      "aria-live",
      "aria-owns",
      "aria-relevant"
    ],
    "requiredProps": [],
    "isAbstract": false
  },
  "doc-glossref": {
    "supportedProps": [
      "aria-atomic",
      "aria-busy",
      "aria-controls",
      "aria-current",
      "aria-describedat",
      "aria-describedby",
      "aria-disabled",
      "aria-dropeffect",
      "aria-expanded",
      "aria-flowto",
      "aria-grabbed",
      "aria-haspopup",
      "aria-hidden",
      "aria-invalid",
      "aria-label",
      "aria-labelledby",
      "aria-live",
      "aria-owns",
      "aria-relevant"
    ],
    "requiredProps": [],
    "isAbstract": false
  },
  "doc-index": {
    "supportedProps": [
      "aria-atomic",
      "aria-busy",
      "aria-controls",
      "aria-current",
      "aria-describedat",
      "aria-describedby",
      "aria-disabled",
      "aria-dropeffect",
      "aria-expanded",
      "aria-flowto",
      "aria-grabbed",
      "aria-haspopup",
      "aria-hidden",
      "aria-invalid",
      "aria-label",
      "aria-labelledby",
      "aria-live",
      "aria-owns",
      "aria-relevant"
    ],
    "requiredProps": [],
    "isAbstract": false
  },
  "doc-introduction": {
    "supportedProps": [
      "aria-atomic",
      "aria-busy",
      "aria-controls",
      "aria-current",
      "aria-describedat",
      "aria-describedby",
      "aria-disabled",
      "aria-dropeffect",
      "aria-expanded",
      "aria-flowto",
      "aria-grabbed",
      "aria-haspopup",
      "aria-hidden",
      "aria-invalid",
      "aria-label",
      "aria-labelledby",
      "aria-live",
      "aria-owns",
      "aria-relevant"
    ],
    "requiredProps": [],
    "isAbstract": false
  },
  "doc-noteref": {
    "supportedProps": [
      "aria-atomic",
      "aria-busy",
      "aria-controls",
      "aria-current",
      "aria-describedat",
      "aria-describedby",
      "aria-disabled",
      "aria-dropeffect",
      "aria-expanded",
      "aria-flowto",
      "aria-grabbed",
      "aria-haspopup",
      "aria-hidden",
      "aria-invalid",
      "aria-label",
      "aria-labelledby",
      "aria-live",
      "aria-owns",
      "aria-relevant"
    ],
    "requiredProps": [],
    "isAbstract": false
  },
  "doc-notice": {
    "supportedProps": [
      "aria-atomic",
      "aria-busy",
      "aria-controls",
      "aria-current",
      "aria-describedat",
      "aria-describedby",
      "aria-disabled",
      "aria-dropeffect",
      "aria-expanded",
      "aria-flowto",
      "aria-grabbed",
      "aria-haspopup",
      "aria-hidden",
      "aria-invalid",
      "aria-label",
      "aria-labelledby",
      "aria-live",
      "aria-owns",
      "aria-relevant"
    ],
    "requiredProps": [],
    "isAbstract": false
  },
  "doc-pagebreak": {
    "supportedProps": [
      "aria-atomic",
      "aria-busy",
      "aria-controls",
      "aria-current",
      "aria-describedat",
      "aria-describedby",
      "aria-disabled",
      "aria-dropeffect",
      "aria-expanded",
      "aria-flowto",
      "aria-grabbed",
      "aria-haspopup",
      "aria-hidden",
      "aria-invalid",
      "aria-label",
      "aria-labelledby",
      "aria-live",
      "aria-orientation",
      "aria-owns",
      "aria-relevant"
    ],
    "requiredProps": [],
    "isAbstract": false
  },
  "doc-pagelist": {
    "supportedProps": [
      "aria-atomic",
      "aria-busy",
      "aria-controls",
      "aria-current",
      "aria-describedat",
      "aria-describedby",
      "aria-disabled",
      "aria-dropeffect",
      "aria-expanded",
      "aria-flowto",
      "aria-grabbed",
      "aria-haspopup",
      "aria-hidden",
      "aria-invalid",
      "aria-label",
      "aria-labelledby",
      "aria-live",
      "aria-owns",
      "aria-relevant"
    ],
    "requiredProps": [],
    "isAbstract": false
  },
  "doc-part": {
    "supportedProps": [
      "aria-atomic",
      "aria-busy",
      "aria-controls",
      "aria-current",
      "aria-describedat",
      "aria-describedby",
      "aria-disabled",
      "aria-dropeffect",
      "aria-expanded",
      "aria-flowto",
      "aria-grabbed",
      "aria-haspopup",
      "aria-hidden",
      "aria-invalid",
      "aria-label",
      "aria-labelledby",
      "aria-live",
      "aria-owns",
      "aria-relevant"
    ],
    "requiredProps": [],
    "isAbstract": false
  },
  "doc-preface": {
    "supportedProps": [
      "aria-atomic",
      "aria-busy",
      "aria-controls",
      "aria-current",
      "aria-describedat",
      "aria-describedby",
      "aria-disabled",
      "aria-dropeffect",
      "aria-expanded",
      "aria-flowto",
      "aria-grabbed",
      "aria-haspopup",
      "aria-hidden",
      "aria-invalid",
      "aria-label",
      "aria-labelledby",
      "aria-live",
      "aria-owns",
      "aria-relevant"
    ],
    "requiredProps": [],
    "isAbstract": false
  },
  "doc-prologue": {
    "supportedProps": [
      "aria-atomic",
      "aria-busy",
      "aria-controls",
      "aria-current",
      "aria-describedat",
      "aria-describedby",
      "aria-disabled",
      "aria-dropeffect",
      "aria-expanded",
      "aria-flowto",
      "aria-grabbed",
      "aria-haspopup",
      "aria-hidden",
      "aria-invalid",
      "aria-label",
      "aria-labelledby",
      "aria-live",
      "aria-owns",
      "aria-relevant"
    ],
    "requiredProps": [],
    "isAbstract": false
  },
  "doc-pullquote": {
    "supportedProps": [],
    "requiredProps": [],
    "isAbstract": false
  },
  "doc-qna": {
    "supportedProps": [
      "aria-atomic",
      "aria-busy",
      "aria-controls",
      "aria-current",
      "aria-describedat",
      "aria-describedby",
      "aria-disabled",
      "aria-dropeffect",
      "aria-expanded",
      "aria-flowto",
      "aria-grabbed",
      "aria-haspopup",
      "aria-hidden",
      "aria-invalid",
      "aria-label",
      "aria-labelledby",
      "aria-live",
      "aria-owns",
      "aria-relevant"
    ],
    "requiredProps": [],
    "isAbstract": false
  },
  "doc-subtitle": {
    "supportedProps": [
      "aria-atomic",
      "aria-busy",
      "aria-controls",
      "aria-current",
      "aria-describedat",
      "aria-describedby",
      "aria-disabled",
      "aria-dropeffect",
      "aria-expanded",
      "aria-flowto",
      "aria-grabbed",
      "aria-haspopup",
      "aria-hidden",
      "aria-invalid",
      "aria-label",
      "aria-labelledby",
      "aria-live",
      "aria-owns",
      "aria-relevant"
    ],
    "requiredProps": [],
    "isAbstract": false
  },
  "doc-tip": {
    "supportedProps": [
      "aria-atomic",
      "aria-busy",
      "aria-controls",
      "aria-current",
      "aria-describedat",
      "aria-describedby",
      "aria-disabled",
      "aria-dropeffect",
      "aria-expanded",
      "aria-flowto",
      "aria-grabbed",
      "aria-haspopup",
      "aria-hidden",
      "aria-invalid",
      "aria-label",
      "aria-labelledby",
      "aria-live",
      "aria-owns",
      "aria-relevant"
    ],
    "requiredProps": [],
    "isAbstract": false
  },
  "doc-toc": {
    "supportedProps": [
      "aria-atomic",
      "aria-busy",
      "aria-controls",
      "aria-current",
      "aria-describedat",
      "aria-describedby",
      "aria-disabled",
      "aria-dropeffect",
      "aria-expanded",
      "aria-flowto",
      "aria-grabbed",
      "aria-haspopup",
      "aria-hidden",
      "aria-invalid",
      "aria-label",
      "aria-labelledby",
      "aria-live",
      "aria-owns",
      "aria-relevant"
    ],
    "requiredProps": [],
    "isAbstract": false
  },
  "document": {
    "requiredProps": [],
    "isAbstract": false,
    "supportedProps": [
      "aria-expanded",
      "aria-atomic",
      "aria-busy",
      "aria-controls",
      "aria-describedby",
      "aria-disabled",
      "aria-dropeffect",
      "aria-flowto",
      "aria-grabbed",
      "aria-haspopup",
      "aria-hidden",
      "aria-invalid",
      "aria-label",
      "aria-labelledby",
      "aria-live",
      "aria-owns",
      "aria-relevant"
    ]
  },
  "form": {
    "requiredProps": [],
    "isAbstract": false,
    "supportedProps": [
      "aria-expanded",
      "aria-atomic",
      "aria-busy",
      "aria-controls",
      "aria-describedby",
      "aria-disabled",
      "aria-dropeffect",
      "aria-flowto",
      "aria-grabbed",
      "aria-haspopup",
      "aria-hidden",
      "aria-invalid",
      "aria-label",
      "aria-labelledby",
      "aria-live",
      "aria-owns",
      "aria-relevant"
    ]
  },
  "grid": {
    "requiredProps": [],
    "isAbstract": false,
    "supportedProps": [
      "aria-level",
      "aria-multiselectable",
      "aria-readonly",
      "aria-activedescendant",
      "aria-atomic",
      "aria-busy",
      "aria-controls",
      "aria-describedby",
      "aria-disabled",
      "aria-dropeffect",
      "aria-flowto",
      "aria-grabbed",
      "aria-haspopup",
      "aria-hidden",
      "aria-invalid",
      "aria-label",
      "aria-labelledby",
      "aria-live",
      "aria-owns",
      "aria-relevant",
      "aria-expanded"
    ]
  },
  "gridcell": {
    "requiredProps": [],
    "isAbstract": false,
    "supportedProps": [
      "aria-readonly",
      "aria-required",
      "aria-selected",
      "aria-expanded",
      "aria-atomic",
      "aria-busy",
      "aria-controls",
      "aria-describedby",
      "aria-disabled",
      "aria-dropeffect",
      "aria-flowto",
      "aria-grabbed",
      "aria-haspopup",
      "aria-hidden",
      "aria-invalid",
      "aria-label",
      "aria-labelledby",
      "aria-live",
      "aria-owns",
      "aria-relevant"
    ]
  },
  "group": {
    "requiredProps": [],
    "isAbstract": false,
    "supportedProps": [
      "aria-activedescendant",
      "aria-expanded",
      "aria-atomic",
      "aria-busy",
      "aria-controls",
      "aria-describedby",
      "aria-disabled",
      "aria-dropeffect",
      "aria-flowto",
      "aria-grabbed",
      "aria-haspopup",
      "aria-hidden",
      "aria-invalid",
      "aria-label",
      "aria-labelledby",
      "aria-live",
      "aria-owns",
      "aria-relevant"
    ]
  },
  "heading": {
    "requiredProps": [],
    "isAbstract": false,
    "supportedProps": [
      "aria-level",
      "aria-expanded",
      "aria-atomic",
      "aria-busy",
      "aria-controls",
      "aria-describedby",
      "aria-disabled",
      "aria-dropeffect",
      "aria-flowto",
      "aria-grabbed",
      "aria-haspopup",
      "aria-hidden",
      "aria-invalid",
      "aria-label",
      "aria-labelledby",
      "aria-live",
      "aria-owns",
      "aria-relevant"
    ]
  },
  "img": {
    "requiredProps": [],
    "isAbstract": false,
    "supportedProps": [
      "aria-expanded",
      "aria-atomic",
      "aria-busy",
      "aria-controls",
      "aria-describedby",
      "aria-disabled",
      "aria-dropeffect",
      "aria-flowto",
      "aria-grabbed",
      "aria-haspopup",
      "aria-hidden",
      "aria-invalid",
      "aria-label",
      "aria-labelledby",
      "aria-live",
      "aria-owns",
      "aria-relevant"
    ]
  },
  "input": {
    "supportedProps": [
      "aria-atomic",
      "aria-busy",
      "aria-controls",
      "aria-describedby",
      "aria-disabled",
      "aria-dropeffect",
      "aria-flowto",
      "aria-grabbed",
      "aria-haspopup",
      "aria-hidden",
      "aria-invalid",
      "aria-label",
      "aria-labelledby",
      "aria-live",
      "aria-owns",
      "aria-relevant"
    ],
    "requiredProps": [],
    "isAbstract": true
  },
  "landmark": {
    "supportedProps": [
      "aria-expanded",
      "aria-atomic",
      "aria-busy",
      "aria-controls",
      "aria-describedby",
      "aria-disabled",
      "aria-dropeffect",
      "aria-flowto",
      "aria-grabbed",
      "aria-haspopup",
      "aria-hidden",
      "aria-invalid",
      "aria-label",
      "aria-labelledby",
      "aria-live",
      "aria-owns",
      "aria-relevant"
    ],
    "requiredProps": [],
    "isAbstract": true
  },
  "link": {
    "requiredProps": [],
    "isAbstract": false,
    "supportedProps": [
      "aria-expanded",
      "aria-atomic",
      "aria-busy",
      "aria-controls",
      "aria-describedby",
      "aria-disabled",
      "aria-dropeffect",
      "aria-flowto",
      "aria-grabbed",
      "aria-haspopup",
      "aria-hidden",
      "aria-invalid",
      "aria-label",
      "aria-labelledby",
      "aria-live",
      "aria-owns",
      "aria-relevant"
    ]
  },
  "list": {
    "requiredProps": [],
    "isAbstract": false,
    "supportedProps": [
      "aria-expanded",
      "aria-atomic",
      "aria-busy",
      "aria-controls",
      "aria-describedby",
      "aria-disabled",
      "aria-dropeffect",
      "aria-flowto",
      "aria-grabbed",
      "aria-haspopup",
      "aria-hidden",
      "aria-invalid",
      "aria-label",
      "aria-labelledby",
      "aria-live",
      "aria-owns",
      "aria-relevant"
    ]
  },
  "listbox": {
    "requiredProps": [],
    "isAbstract": false,
    "supportedProps": [
      "aria-multiselectable",
      "aria-required",
      "aria-expanded",
      "aria-atomic",
      "aria-busy",
      "aria-controls",
      "aria-describedby",
      "aria-disabled",
      "aria-dropeffect",
      "aria-flowto",
      "aria-grabbed",
      "aria-haspopup",
      "aria-hidden",
      "aria-invalid",
      "aria-label",
      "aria-labelledby",
      "aria-live",
      "aria-owns",
      "aria-relevant",
      "aria-activedescendant"
    ]
  },
  "listitem": {
    "requiredProps": [],
    "isAbstract": false,
    "supportedProps": [
      "aria-level",
      "aria-posinset",
      "aria-setsize",
      "aria-expanded",
      "aria-atomic",
      "aria-busy",
      "aria-controls",
      "aria-describedby",
      "aria-disabled",
      "aria-dropeffect",
      "aria-flowto",
      "aria-grabbed",
      "aria-haspopup",
      "aria-hidden",
      "aria-invalid",
      "aria-label",
      "aria-labelledby",
      "aria-live",
      "aria-owns",
      "aria-relevant"
    ]
  },
  "log": {
    "requiredProps": [],
    "isAbstract": false,
    "supportedProps": [
      "aria-expanded",
      "aria-atomic",
      "aria-busy",
      "aria-controls",
      "aria-describedby",
      "aria-disabled",
      "aria-dropeffect",
      "aria-flowto",
      "aria-grabbed",
      "aria-haspopup",
      "aria-hidden",
      "aria-invalid",
      "aria-label",
      "aria-labelledby",
      "aria-live",
      "aria-owns",
      "aria-relevant"
    ]
  },
  "main": {
    "requiredProps": [],
    "isAbstract": false,
    "supportedProps": [
      "aria-expanded",
      "aria-atomic",
      "aria-busy",
      "aria-controls",
      "aria-describedby",
      "aria-disabled",
      "aria-dropeffect",
      "aria-flowto",
      "aria-grabbed",
      "aria-haspopup",
      "aria-hidden",
      "aria-invalid",
      "aria-label",
      "aria-labelledby",
      "aria-live",
      "aria-owns",
      "aria-relevant"
    ]
  },
  "marquee": {
    "requiredProps": [],
    "isAbstract": false,
    "supportedProps": [
      "aria-expanded",
      "aria-atomic",
      "aria-busy",
      "aria-controls",
      "aria-describedby",
      "aria-disabled",
      "aria-dropeffect",
      "aria-flowto",
      "aria-grabbed",
      "aria-haspopup",
      "aria-hidden",
      "aria-invalid",
      "aria-label",
      "aria-labelledby",
      "aria-live",
      "aria-owns",
      "aria-relevant"
    ]
  },
  "math": {
    "requiredProps": [],
    "isAbstract": false,
    "supportedProps": [
      "aria-expanded",
      "aria-atomic",
      "aria-busy",
      "aria-controls",
      "aria-describedby",
      "aria-disabled",
      "aria-dropeffect",
      "aria-flowto",
      "aria-grabbed",
      "aria-haspopup",
      "aria-hidden",
      "aria-invalid",
      "aria-label",
      "aria-labelledby",
      "aria-live",
      "aria-owns",
      "aria-relevant"
    ]
  },
  "menu": {
    "requiredProps": [],
    "isAbstract": false,
    "supportedProps": [
      "aria-expanded",
      "aria-atomic",
      "aria-busy",
      "aria-controls",
      "aria-describedby",
      "aria-disabled",
      "aria-dropeffect",
      "aria-flowto",
      "aria-grabbed",
      "aria-haspopup",
      "aria-hidden",
      "aria-invalid",
      "aria-label",
      "aria-labelledby",
      "aria-live",
      "aria-owns",
      "aria-relevant",
      "aria-activedescendant"
    ]
  },
  "menubar": {
    "requiredProps": [],
    "isAbstract": false,
    "supportedProps": [
      "aria-expanded",
      "aria-atomic",
      "aria-busy",
      "aria-controls",
      "aria-describedby",
      "aria-disabled",
      "aria-dropeffect",
      "aria-flowto",
      "aria-grabbed",
      "aria-haspopup",
      "aria-hidden",
      "aria-invalid",
      "aria-label",
      "aria-labelledby",
      "aria-live",
      "aria-owns",
      "aria-relevant",
      "aria-activedescendant"
    ]
  },
  "menuitem": {
    "requiredProps": [],
    "isAbstract": false,
    "supportedProps": [
      "aria-atomic",
      "aria-busy",
      "aria-controls",
      "aria-describedby",
      "aria-disabled",
      "aria-dropeffect",
      "aria-flowto",
      "aria-grabbed",
      "aria-haspopup",
      "aria-hidden",
      "aria-invalid",
      "aria-label",
      "aria-labelledby",
      "aria-live",
      "aria-owns",
      "aria-relevant"
    ]
  },
  "menuitemcheckbox": {
    "requiredProps": [],
    "isAbstract": false,
    "supportedProps": [
      "aria-checked",
      "aria-atomic",
      "aria-busy",
      "aria-controls",
      "aria-describedby",
      "aria-disabled",
      "aria-dropeffect",
      "aria-flowto",
      "aria-grabbed",
      "aria-haspopup",
      "aria-hidden",
      "aria-invalid",
      "aria-label",
      "aria-labelledby",
      "aria-live",
      "aria-owns",
      "aria-relevant"
    ]
  },
  "menuitemradio": {
    "requiredProps": [],
    "isAbstract": false,
    "supportedProps": [
      "aria-checked",
      "aria-atomic",
      "aria-busy",
      "aria-controls",
      "aria-describedby",
      "aria-disabled",
      "aria-dropeffect",
      "aria-flowto",
      "aria-grabbed",
      "aria-haspopup",
      "aria-hidden",
      "aria-invalid",
      "aria-label",
      "aria-labelledby",
      "aria-live",
      "aria-owns",
      "aria-relevant",
      "aria-posinset",
      "aria-selected",
      "aria-setsize"
    ]
  },
  "navigation": {
    "requiredProps": [],
    "isAbstract": false,
    "supportedProps": [
      "aria-expanded",
      "aria-atomic",
      "aria-busy",
      "aria-controls",
      "aria-describedby",
      "aria-disabled",
      "aria-dropeffect",
      "aria-flowto",
      "aria-grabbed",
      "aria-haspopup",
      "aria-hidden",
      "aria-invalid",
      "aria-label",
      "aria-labelledby",
      "aria-live",
      "aria-owns",
      "aria-relevant"
    ]
  },
  "note": {
    "requiredProps": [],
    "isAbstract": false,
    "supportedProps": [
      "aria-expanded",
      "aria-atomic",
      "aria-busy",
      "aria-controls",
      "aria-describedby",
      "aria-disabled",
      "aria-dropeffect",
      "aria-flowto",
      "aria-grabbed",
      "aria-haspopup",
      "aria-hidden",
      "aria-invalid",
      "aria-label",
      "aria-labelledby",
      "aria-live",
      "aria-owns",
      "aria-relevant"
    ]
  },
  "option": {
    "requiredProps": [],
    "isAbstract": false,
    "supportedProps": [
      "aria-checked",
      "aria-posinset",
      "aria-selected",
      "aria-setsize",
      "aria-atomic",
      "aria-busy",
      "aria-controls",
      "aria-describedby",
      "aria-disabled",
      "aria-dropeffect",
      "aria-flowto",
      "aria-grabbed",
      "aria-haspopup",
      "aria-hidden",
      "aria-invalid",
      "aria-label",
      "aria-labelledby",
      "aria-live",
      "aria-owns",
      "aria-relevant"
    ]
  },
  "presentation": {
    "requiredProps": [],
    "isAbstract": false,
    "supportedProps": [
      "aria-atomic",
      "aria-busy",
      "aria-controls",
      "aria-describedby",
      "aria-disabled",
      "aria-dropeffect",
      "aria-flowto",
      "aria-grabbed",
      "aria-haspopup",
      "aria-hidden",
      "aria-invalid",
      "aria-label",
      "aria-labelledby",
      "aria-live",
      "aria-owns",
      "aria-relevant"
    ]
  },
  "progressbar": {
    "requiredProps": [],
    "isAbstract": false,
    "supportedProps": [
      "aria-valuemax",
      "aria-valuemin",
      "aria-valuenow",
      "aria-valuetext",
      "aria-atomic",
      "aria-busy",
      "aria-controls",
      "aria-describedby",
      "aria-disabled",
      "aria-dropeffect",
      "aria-flowto",
      "aria-grabbed",
      "aria-haspopup",
      "aria-hidden",
      "aria-invalid",
      "aria-label",
      "aria-labelledby",
      "aria-live",
      "aria-owns",
      "aria-relevant"
    ]
  },
  "radio": {
    "requiredProps": [],
    "isAbstract": false,
    "supportedProps": [
      "aria-checked",
      "aria-atomic",
      "aria-busy",
      "aria-controls",
      "aria-describedby",
      "aria-disabled",
      "aria-dropeffect",
      "aria-flowto",
      "aria-grabbed",
      "aria-haspopup",
      "aria-hidden",
      "aria-invalid",
      "aria-label",
      "aria-labelledby",
      "aria-live",
      "aria-owns",
      "aria-relevant",
      "aria-posinset",
      "aria-selected",
      "aria-setsize"
    ]
  },
  "radiogroup": {
    "requiredProps": [],
    "isAbstract": false,
    "supportedProps": [
      "aria-required",
      "aria-activedescendant",
      "aria-atomic",
      "aria-busy",
      "aria-controls",
      "aria-describedby",
      "aria-disabled",
      "aria-dropeffect",
      "aria-flowto",
      "aria-grabbed",
      "aria-haspopup",
      "aria-hidden",
      "aria-invalid",
      "aria-label",
      "aria-labelledby",
      "aria-live",
      "aria-owns",
      "aria-relevant",
      "aria-expanded"
    ]
  },
  "range": {
    "supportedProps": [
      "aria-valuemax",
      "aria-valuemin",
      "aria-valuenow",
      "aria-valuetext",
      "aria-atomic",
      "aria-busy",
      "aria-controls",
      "aria-describedby",
      "aria-disabled",
      "aria-dropeffect",
      "aria-flowto",
      "aria-grabbed",
      "aria-haspopup",
      "aria-hidden",
      "aria-invalid",
      "aria-label",
      "aria-labelledby",
      "aria-live",
      "aria-owns",
      "aria-relevant"
    ],
    "requiredProps": [],
    "isAbstract": true
  },
  "region": {
    "requiredProps": [],
    "isAbstract": false,
    "supportedProps": [
      "aria-expanded",
      "aria-atomic",
      "aria-busy",
      "aria-controls",
      "aria-describedby",
      "aria-disabled",
      "aria-dropeffect",
      "aria-flowto",
      "aria-grabbed",
      "aria-haspopup",
      "aria-hidden",
      "aria-invalid",
      "aria-label",
      "aria-labelledby",
      "aria-live",
      "aria-owns",
      "aria-relevant"
    ]
  },
  "roletype": {
    "supportedProps": [
      "aria-atomic",
      "aria-busy",
      "aria-controls",
      "aria-describedby",
      "aria-disabled",
      "aria-dropeffect",
      "aria-flowto",
      "aria-grabbed",
      "aria-haspopup",
      "aria-hidden",
      "aria-invalid",
      "aria-label",
      "aria-labelledby",
      "aria-live",
      "aria-owns",
      "aria-relevant"
    ],
    "requiredProps": [],
    "isAbstract": true
  },
  "row": {
    "requiredProps": [],
    "isAbstract": false,
    "supportedProps": [
      "aria-level",
      "aria-selected",
      "aria-activedescendant",
      "aria-expanded",
      "aria-atomic",
      "aria-busy",
      "aria-controls",
      "aria-describedby",
      "aria-disabled",
      "aria-dropeffect",
      "aria-flowto",
      "aria-grabbed",
      "aria-haspopup",
      "aria-hidden",
      "aria-invalid",
      "aria-label",
      "aria-labelledby",
      "aria-live",
      "aria-owns",
      "aria-relevant"
    ]
  },
  "rowgroup": {
    "requiredProps": [],
    "isAbstract": false,
    "supportedProps": [
      "aria-activedescendant",
      "aria-expanded",
      "aria-atomic",
      "aria-busy",
      "aria-controls",
      "aria-describedby",
      "aria-disabled",
      "aria-dropeffect",
      "aria-flowto",
      "aria-grabbed",
      "aria-haspopup",
      "aria-hidden",
      "aria-invalid",
      "aria-label",
      "aria-labelledby",
      "aria-live",
      "aria-owns",
      "aria-relevant"
    ]
  },
  "rowheader": {
    "requiredProps": [],
    "isAbstract": false,
    "supportedProps": [
      "aria-sort",
      "aria-readonly",
      "aria-required",
      "aria-selected",
      "aria-expanded",
      "aria-atomic",
      "aria-busy",
      "aria-controls",
      "aria-describedby",
      "aria-disabled",
      "aria-dropeffect",
      "aria-flowto",
      "aria-grabbed",
      "aria-haspopup",
      "aria-hidden",
      "aria-invalid",
      "aria-label",
      "aria-labelledby",
      "aria-live",
      "aria-owns",
      "aria-relevant"
    ]
  },
  "search": {
    "requiredProps": [],
    "isAbstract": false,
    "supportedProps": [
      "aria-expanded",
      "aria-atomic",
      "aria-busy",
      "aria-controls",
      "aria-describedby",
      "aria-disabled",
      "aria-dropeffect",
      "aria-flowto",
      "aria-grabbed",
      "aria-haspopup",
      "aria-hidden",
      "aria-invalid",
      "aria-label",
      "aria-labelledby",
      "aria-live",
      "aria-owns",
      "aria-relevant"
    ]
  },
  "section": {
    "supportedProps": [
      "aria-expanded",
      "aria-atomic",
      "aria-busy",
      "aria-controls",
      "aria-describedby",
      "aria-disabled",
      "aria-dropeffect",
      "aria-flowto",
      "aria-grabbed",
      "aria-haspopup",
      "aria-hidden",
      "aria-invalid",
      "aria-label",
      "aria-labelledby",
      "aria-live",
      "aria-owns",
      "aria-relevant"
    ],
    "requiredProps": [],
    "isAbstract": true
  },
  "sectionhead": {
    "supportedProps": [
      "aria-expanded",
      "aria-atomic",
      "aria-busy",
      "aria-controls",
      "aria-describedby",
      "aria-disabled",
      "aria-dropeffect",
      "aria-flowto",
      "aria-grabbed",
      "aria-haspopup",
      "aria-hidden",
      "aria-invalid",
      "aria-label",
      "aria-labelledby",
      "aria-live",
      "aria-owns",
      "aria-relevant"
    ],
    "requiredProps": [],
    "isAbstract": true
  },
  "select": {
    "supportedProps": [
      "aria-activedescendant",
      "aria-atomic",
      "aria-busy",
      "aria-controls",
      "aria-describedby",
      "aria-disabled",
      "aria-dropeffect",
      "aria-flowto",
      "aria-grabbed",
      "aria-haspopup",
      "aria-hidden",
      "aria-invalid",
      "aria-label",
      "aria-labelledby",
      "aria-live",
      "aria-owns",
      "aria-relevant",
      "aria-expanded"
    ],
    "requiredProps": [],
    "isAbstract": true
  },
  "separator": {
    "requiredProps": [],
    "isAbstract": false,
    "supportedProps": [
      "aria-expanded",
      "aria-orientation",
      "aria-atomic",
      "aria-busy",
      "aria-controls",
      "aria-describedby",
      "aria-disabled",
      "aria-dropeffect",
      "aria-flowto",
      "aria-grabbed",
      "aria-haspopup",
      "aria-hidden",
      "aria-invalid",
      "aria-label",
      "aria-labelledby",
      "aria-live",
      "aria-owns",
      "aria-relevant"
    ]
  },
  "scrollbar": {
    "requiredProps": [
      "aria-controls",
      "aria-orientation",
      "aria-valuemax",
      "aria-valuemin",
      "aria-valuenow"
    ],
    "isAbstract": false,
    "supportedProps": [
      "aria-controls",
      "aria-orientation",
      "aria-valuemax",
      "aria-valuemin",
      "aria-valuenow",
      "aria-atomic",
      "aria-busy",
      "aria-describedby",
      "aria-disabled",
      "aria-dropeffect",
      "aria-flowto",
      "aria-grabbed",
      "aria-haspopup",
      "aria-hidden",
      "aria-invalid",
      "aria-label",
      "aria-labelledby",
      "aria-live",
      "aria-owns",
      "aria-relevant",
      "aria-valuetext"
    ]
  },
  "slider": {
    "requiredProps": [
      "aria-valuemax",
      "aria-valuemin",
      "aria-valuenow"
    ],
    "isAbstract": false,
    "supportedProps": [
      "aria-valuemax",
      "aria-valuemin",
      "aria-valuenow",
      "aria-orientation",
      "aria-atomic",
      "aria-busy",
      "aria-controls",
      "aria-describedby",
      "aria-disabled",
      "aria-dropeffect",
      "aria-flowto",
      "aria-grabbed",
      "aria-haspopup",
      "aria-hidden",
      "aria-invalid",
      "aria-label",
      "aria-labelledby",
      "aria-live",
      "aria-owns",
      "aria-relevant",
      "aria-valuetext"
    ]
  },
  "spinbutton": {
    "requiredProps": [
      "aria-valuemax",
      "aria-valuemin",
      "aria-valuenow"
    ],
    "isAbstract": false,
    "supportedProps": [
      "aria-valuemax",
      "aria-valuemin",
      "aria-valuenow",
      "aria-required",
      "aria-atomic",
      "aria-busy",
      "aria-controls",
      "aria-describedby",
      "aria-disabled",
      "aria-dropeffect",
      "aria-flowto",
      "aria-grabbed",
      "aria-haspopup",
      "aria-hidden",
      "aria-invalid",
      "aria-label",
      "aria-labelledby",
      "aria-live",
      "aria-owns",
      "aria-relevant",
      "aria-valuetext"
    ]
  },
  "status": {
    "requiredProps": [],
    "isAbstract": false,
    "supportedProps": [
      "aria-expanded",
      "aria-atomic",
      "aria-busy",
      "aria-controls",
      "aria-describedby",
      "aria-disabled",
      "aria-dropeffect",
      "aria-flowto",
      "aria-grabbed",
      "aria-haspopup",
      "aria-hidden",
      "aria-invalid",
      "aria-label",
      "aria-labelledby",
      "aria-live",
      "aria-owns",
      "aria-relevant"
    ]
  },
  "structure": {
    "supportedProps": [
      "aria-atomic",
      "aria-busy",
      "aria-controls",
      "aria-describedby",
      "aria-disabled",
      "aria-dropeffect",
      "aria-flowto",
      "aria-grabbed",
      "aria-haspopup",
      "aria-hidden",
      "aria-invalid",
      "aria-label",
      "aria-labelledby",
      "aria-live",
      "aria-owns",
      "aria-relevant"
    ],
    "requiredProps": [],
    "isAbstract": true
  },
  "tab": {
    "requiredProps": [],
    "isAbstract": false,
    "supportedProps": [
      "aria-selected",
      "aria-expanded",
      "aria-atomic",
      "aria-busy",
      "aria-controls",
      "aria-describedby",
      "aria-disabled",
      "aria-dropeffect",
      "aria-flowto",
      "aria-grabbed",
      "aria-haspopup",
      "aria-hidden",
      "aria-invalid",
      "aria-label",
      "aria-labelledby",
      "aria-live",
      "aria-owns",
      "aria-relevant"
    ]
  },
  "tablist": {
    "requiredProps": [],
    "isAbstract": false,
    "supportedProps": [
      "aria-level",
      "aria-activedescendant",
      "aria-atomic",
      "aria-busy",
      "aria-controls",
      "aria-describedby",
      "aria-disabled",
      "aria-dropeffect",
      "aria-flowto",
      "aria-grabbed",
      "aria-haspopup",
      "aria-hidden",
      "aria-invalid",
      "aria-label",
      "aria-labelledby",
      "aria-live",
      "aria-owns",
      "aria-relevant",
      "aria-expanded"
    ]
  },
  "tabpanel": {
    "requiredProps": [],
    "isAbstract": false,
    "supportedProps": [
      "aria-expanded",
      "aria-atomic",
      "aria-busy",
      "aria-controls",
      "aria-describedby",
      "aria-disabled",
      "aria-dropeffect",
      "aria-flowto",
      "aria-grabbed",
      "aria-haspopup",
      "aria-hidden",
      "aria-invalid",
      "aria-label",
      "aria-labelledby",
      "aria-live",
      "aria-owns",
      "aria-relevant"
    ]
  },
  "textbox": {
    "requiredProps": [],
    "isAbstract": false,
    "supportedProps": [
      "aria-activedescendant",
      "aria-autocomplete",
      "aria-multiline",
      "aria-readonly",
      "aria-required",
      "aria-atomic",
      "aria-busy",
      "aria-controls",
      "aria-describedby",
      "aria-disabled",
      "aria-dropeffect",
      "aria-flowto",
      "aria-grabbed",
      "aria-haspopup",
      "aria-hidden",
      "aria-invalid",
      "aria-label",
      "aria-labelledby",
      "aria-live",
      "aria-owns",
      "aria-relevant"
    ]
  },
  "timer": {
    "requiredProps": [],
    "isAbstract": false,
    "supportedProps": [
      "aria-expanded",
      "aria-atomic",
      "aria-busy",
      "aria-controls",
      "aria-describedby",
      "aria-disabled",
      "aria-dropeffect",
      "aria-flowto",
      "aria-grabbed",
      "aria-haspopup",
      "aria-hidden",
      "aria-invalid",
      "aria-label",
      "aria-labelledby",
      "aria-live",
      "aria-owns",
      "aria-relevant"
    ]
  },
  "toolbar": {
    "requiredProps": [],
    "isAbstract": false,
    "supportedProps": [
      "aria-activedescendant",
      "aria-expanded",
      "aria-atomic",
      "aria-busy",
      "aria-controls",
      "aria-describedby",
      "aria-disabled",
      "aria-dropeffect",
      "aria-flowto",
      "aria-grabbed",
      "aria-haspopup",
      "aria-hidden",
      "aria-invalid",
      "aria-label",
      "aria-labelledby",
      "aria-live",
      "aria-owns",
      "aria-relevant"
    ]
  },
  "tooltip": {
    "requiredProps": [],
    "isAbstract": false,
    "supportedProps": [
      "aria-expanded",
      "aria-atomic",
      "aria-busy",
      "aria-controls",
      "aria-describedby",
      "aria-disabled",
      "aria-dropeffect",
      "aria-flowto",
      "aria-grabbed",
      "aria-haspopup",
      "aria-hidden",
      "aria-invalid",
      "aria-label",
      "aria-labelledby",
      "aria-live",
      "aria-owns",
      "aria-relevant"
    ]
  },
  "tree": {
    "requiredProps": [],
    "isAbstract": false,
    "supportedProps": [
      "aria-multiselectable",
      "aria-required",
      "aria-activedescendant",
      "aria-atomic",
      "aria-busy",
      "aria-controls",
      "aria-describedby",
      "aria-disabled",
      "aria-dropeffect",
      "aria-flowto",
      "aria-grabbed",
      "aria-haspopup",
      "aria-hidden",
      "aria-invalid",
      "aria-label",
      "aria-labelledby",
      "aria-live",
      "aria-owns",
      "aria-relevant",
      "aria-expanded"
    ]
  },
  "treegrid": {
    "requiredProps": [],
    "isAbstract": false,
    "supportedProps": [
      "aria-level",
      "aria-multiselectable",
      "aria-readonly",
      "aria-activedescendant",
      "aria-atomic",
      "aria-busy",
      "aria-controls",
      "aria-describedby",
      "aria-disabled",
      "aria-dropeffect",
      "aria-flowto",
      "aria-grabbed",
      "aria-haspopup",
      "aria-hidden",
      "aria-invalid",
      "aria-label",
      "aria-labelledby",
      "aria-live",
      "aria-owns",
      "aria-relevant",
      "aria-expanded",
      "aria-required"
    ]
  },
  "treeitem": {
    "requiredProps": [],
    "isAbstract": false,
    "supportedProps": [
      "aria-level",
      "aria-posinset",
      "aria-setsize",
      "aria-expanded",
      "aria-atomic",
      "aria-busy",
      "aria-controls",
      "aria-describedby",
      "aria-disabled",
      "aria-dropeffect",
      "aria-flowto",
      "aria-grabbed",
      "aria-haspopup",
      "aria-hidden",
      "aria-invalid",
      "aria-label",
      "aria-labelledby",
      "aria-live",
      "aria-owns",
      "aria-relevant",
      "aria-checked",
      "aria-selected"
    ]
  },
  "widget": {
    "supportedProps": [
      "aria-atomic",
      "aria-busy",
      "aria-controls",
      "aria-describedby",
      "aria-disabled",
      "aria-dropeffect",
      "aria-flowto",
      "aria-grabbed",
      "aria-haspopup",
      "aria-hidden",
      "aria-invalid",
      "aria-label",
      "aria-labelledby",
      "aria-live",
      "aria-owns",
      "aria-relevant"
    ],
    "requiredProps": [],
    "isAbstract": true
  },
  "window": {
    "supportedProps": [
      "aria-expanded",
      "aria-atomic",
      "aria-busy",
      "aria-controls",
      "aria-describedby",
      "aria-disabled",
      "aria-dropeffect",
      "aria-flowto",
      "aria-grabbed",
      "aria-haspopup",
      "aria-hidden",
      "aria-invalid",
      "aria-label",
      "aria-labelledby",
      "aria-live",
      "aria-owns",
      "aria-relevant"
    ],
    "requiredProps": [],
    "isAbstract": true
  }
}
